<speak xmlns="http://www.w3.org/2001/10/synthesis" xmlns:mstts="http://www.w3.org/2001/mstts" xmlns:emo="http://www.w3.org/2009/10/emotionml" version="1.0" xml:lang="en-US">
<voice name="en-US-BrianNeural">
So Andrew, I've been reading about the face detection capabilities of Azure AI services. It's fascinating how it can assign an ID to a detected face and compare it with other faces. Can you tell me more about how this works?
</voice>
<voice name="en-US-AndrewNeural">
Absolutely, Brian. When a face is detected by the Face service, it assigns a unique ID to it. This ID is stored in the service resource for 24 hours. It's important to note that the ID doesn't reveal the individual's identity, it's just based on their facial features.
</voice>
<voice name="en-US-BrianNeural">
That's interesting. So, how can we use this ID to compare faces?
</voice>
<voice name="en-US-AndrewNeural">
Well, once the face ID is cached, you can use subsequent images to compare new faces with the cached identity. This allows you to determine if the faces are similar, meaning they share similar facial features. It can also be used to verify if the same person appears in two different images.
</voice>
<voice name="en-US-BrianNeural">
That's really useful. Can you give me an example of how this face comparison can be applied in a real-world scenario?
</voice>
<voice name="en-US-AndrewNeural">
Sure, let's say you have a system that requires verifying if the same person is present on two occasions without knowing their actual identity. For instance, you could use images of people as they enter and leave a secured space. By comparing the faces detected in these images, you can verify that everyone who entered the space has also left.
</voice>
<voice name="en-US-BrianNeural">
Ah, I see. So it's a way to ensure that no one is left behind or that unauthorized individuals are not present. That's really powerful.
</voice>
<voice name="en-US-AndrewNeural">
Absolutely, Brian. It's a valuable capability for security and access control systems.
</voice>
<voice name="en-US-BrianNeural">
I can definitely see the potential applications of this feature. Thanks for explaining it, Andrew.
</voice>
<voice name="en-US-AndrewNeural">
You're welcome, Brian. 
</voice>
</speak>